{
	"configurations" : 
	[
		{
			"directories" : 
			[
				{
					"build" : ".",
					"jsonFile" : "directory-.-Debug-f5ebdc15457944623624.json",
					"minimumCMakeVersion" : 
					{
						"string" : "3.16"
					},
					"projectIndex" : 0,
					"source" : ".",
					"targetIndexes" : 
					[
						0
					]
				}
			],
			"name" : "Debug",
			"projects" : 
			[
				{
					"directoryIndexes" : 
					[
						0
					],
					"name" : "ProjectAlpha",
					"targetIndexes" : 
					[
						0
					]
				}
			],
			"targets" : 
			[
				{
					"directoryIndex" : 0,
					"id" : "ProjectAlpha::@6890427a1f51a3e7e1df",
					"jsonFile" : "target-ProjectAlpha-Debug-a48e872b697d4b8d8159.json",
					"name" : "ProjectAlpha",
					"projectIndex" : 0
				}
			]
		}
	],
	"kind" : "codemodel",
	"paths" : 
	{
		"build" : "/Users/torgerau/Desktop/Uni Stuff/POOSE/projekt123sts/PriorityQueue/build",
		"source" : "/Users/torgerau/Desktop/Uni Stuff/POOSE/projekt123sts/PriorityQueue"
	},
	"version" : 
	{
		"major" : 2,
		"minor" : 5
	}
}
